nf_gym
