Metadata-Version: 1.0
Name: nf-gym
Version: 0.0.74
Summary: A OpenAI Gym Env for nfbot
Home-page: UNKNOWN
Author: UNKNOWN
Author-email: UNKNOWN
License: UNKNOWN
Platform: UNKNOWN
